{
  "Backquote": "`",
  "Backslash": "\\",
  "BracketLeft": "]",
  "BracketRight": "[",
  "Comma": "،",
  "Digit0": "٠",
  "Digit1": "١",
  "Digit2": "٢",
  "Digit3": "٣",
  "Digit4": "٤",
  "Digit5": "٥",
  "Digit6": "٦",
  "Digit7": "٧",
  "Digit8": "٨",
  "Digit9": "٩",
  "Equal": "=",
  "IntlBackslash": "|",
  "IntlRo": "",
  "IntlYen": "",
  "KeyA": "ا",
  "KeyB": "ب",
  "KeyC": "چ",
  "KeyD": "د",
  "KeyE": "ى",
  "KeyF": "ف",
  "KeyG": "ݢ",
  "KeyH": "ه",
  "KeyI": "ئ",
  "KeyJ": "ج",
  "KeyK": "ک",
  "KeyL": "ل",
  "KeyM": "م",
  "KeyN": "ن",
  "KeyO": "ء",
  "KeyP": "ڤ",
  "KeyQ": "ق",
  "KeyR": "ر",
  "KeyS": "س",
  "KeyT": "ت",
  "KeyU": "ؤ",
  "KeyV": "ث",
  "KeyW": "و",
  "KeyX": "خ",
  "KeyY": "ي",
  "KeyZ": "ز",
  "Minus": "-",
  "Period": ".",
  "Quote": "«",
  "Semicolon": "؛",
  "Slash": "/",
  "Space": " "
}