{
  "Backquote": "᠍",
  "Backslash": "",
  "BracketLeft": "",
  "BracketRight": "",
  "Comma": "᠈",
  "Digit0": "",
  "Digit1": "",
  "Digit2": "",
  "Digit3": "",
  "Digit4": "",
  "Digit5": "",
  "Digit6": "",
  "Digit7": "",
  "Digit8": "",
  "Digit9": "",
  "Equal": "",
  "IntlBackslash": "<",
  "IntlRo": "",
  "IntlYen": "",
  "KeyA": "ᢒ",
  "KeyB": "ᢨ",
  "KeyC": "ᢤ",
  "KeyD": "ᢛ",
  "KeyE": "ᢂ",
  "KeyF": "ᢜ",
  "KeyG": "ᢝ",
  "KeyH": "ᢞ",
  "KeyI": "ᢇ",
  "KeyJ": "ᢟ",
  "KeyK": "ᢠ",
  "KeyL": "ᢡ",
  "KeyM": "",
  "KeyN": "ᢪ",
  "KeyO": "ᢈ",
  "KeyP": "ᢏ",
  "KeyQ": "ᢀ",
  "KeyR": "ᢃ",
  "KeyS": "ᢚ",
  "KeyT": "ᢄ",
  "KeyU": "ᢆ",
  "KeyV": "ᢥ",
  "KeyW": "ᢁ",
  "KeyX": "ᢣ",
  "KeyY": "ᢅ",
  "KeyZ": "ᢢ",
  "Minus": " ",
  "Period": "᠉",
  "Quote": "᠋",
  "Semicolon": "",
  "Slash": "",
  "Space": " "
}